flask_sqlx/__init__.py
flask_sqlx/__version__.py
flask_sqlx/db.py
flask_sqlx/exceptions.py
flask_sqlx/sql_loader.py
flask_sqlx-0.0.1.dist-info/METADATA
flask_sqlx-0.0.1.dist-info/WHEEL
flask_sqlx-0.0.1.dist-info/top_level.txt
flask_sqlx-0.0.1.dist-info/RECORD
